toposim/__init__.py
toposim-0.1.0.dist-info/WHEEL
toposim-0.1.0.dist-info/METADATA
toposim-0.1.0.dist-info/RECORD
