Metadata-Version: 2.1
Name: toposim
Version: 0.1.0
Summary: 
Author: yajiez
Author-email: yajiez.me@gmail.com
Requires-Python: >=3.7,<4.0
Classifier: Programming Language :: Python :: 3
Classifier: Programming Language :: Python :: 3.7
Classifier: Programming Language :: Python :: 3.8
Requires-Dist: ipython (>=7.10.2,<8.0.0)
Requires-Dist: numpy (>=1.17.4,<2.0.0)
Requires-Dist: pandas (>=0.25.3,<0.26.0)
Requires-Dist: scikit-learn (>=0.22,<0.23)
Requires-Dist: seaborn (>=0.9.0,<0.10.0)
Requires-Dist: torch (>=1.3.1,<2.0.0)
